[{
        "medikament_id": 1,
        "verordnung_id": 1,
        "applikationszeitpunkt": "[{\"tag\":\"Montag\",\"zeiten\": [{\"zeit\":\"08:00\"}, {\"zeit\":\"12:00\"},{\"zeit\":\"16:00\"}, {\"zeit\":\"18:00\"}]}]",
        "beginn": "2015-12-31T23:00:00.000Z",
        "ende": "2016-01-10T23:00:00.000Z",
        "patient_id": 1,
        "personal_id": 2,
        "station_id": 1,
        "dosierung": 2,
        "selbstverordnung": 1,
        "medikamentname": "ASS 500-1A Pharma",
        "darreichungsform": "peroral",
        "wirkstärke": 500,
        "einheit": "Tablette",
        "wirkstoffbezeichnung": "Acetylsalicylsäure",
        "applikationshinweis": "Nehmen Sie das Arzneimittel mit Flüssigkeit (z.B. 1 Glas Wasser) ein.",
        "name": "Miske",
        "vorname": "Alex",
        "anschrift": "Augustdorf",
        "telefonnummer": 12345678,
        "aufnahmedatum": "2015-12-31T23:00:00.000Z",
        "entlassungsdatum": "2016-01-11T23:00:00.000Z",
        "geburtsdatum": "1989-09-15T22:00:00.000Z",
        "krankenversicherung": "AOK",
        "grund": "Aua",
        "zimmer": 1
    }, {
        "medikament_id": 1,
        "verordnung_id": 1,
        "applikationszeitpunkt": "[{\"tag\":\"Montag\",\"zeiten\": [{\"zeit\":\"08:00\"}, {\"zeit\":\"12:00\"},{\"zeit\":\"16:00\"}, {\"zeit\":\"18:00\"}]}]",
        "beginn": "2015-12-31T23:00:00.000Z",
        "ende": "2016-01-10T23:00:00.000Z",
        "patient_id": 2,
        "personal_id": 2,
        "station_id": 1,
        "dosierung": 2,
        "selbstverordnung": 1,
        "medikamentname": "ASS 500-1A Pharma",
        "darreichungsform": "peroral",
        "wirkstärke": 500,
        "einheit": "Tablette",
        "wirkstoffbezeichnung": "Acetylsalicylsäure",
        "applikationshinweis": "Nehmen Sie das Arzneimittel mit Flüssigkeit (z.B. 1 Glas Wasser) ein.",
        "name": "Mustermann",
        "vorname": "Max",
        "anschrift": "Musterhausen",
        "telefonnummer": 12345678,
        "aufnahmedatum": "2016-01-04T23:00:00.000Z",
        "entlassungsdatum": "2016-01-26T23:00:00.000Z",
        "geburtsdatum": "1980-10-10T22:00:00.000Z",
        "krankenversicherung": "AOK",
        "grund": "Auch Aua",
        "zimmer": 2
    }, {
        "medikament_id": 2,
        "verordnung_id": 2,
        "applikationszeitpunkt": "[{\"tag\":\"Montag\",\"zeiten\": [{\"zeit\":\"08:00\"}, {\"zeit\":\"16:00\"}]},{\"tag\":\"Mittwoch\",\"zeiten\": [{\"zeit\":\"08:00\"}, {\"zeit\":\"16:00\"}]}]",
        "beginn": "2015-12-31T23:00:00.000Z",
        "ende": "2016-01-10T23:00:00.000Z",
        "patient_id": 1,
        "personal_id": 2,
        "station_id": 1,
        "dosierung": 1,
        "selbstverordnung": 1,
        "medikamentname": "IBUFLAM 800mg",
        "darreichungsform": "peroral",
        "wirkstärke": 800,
        "einheit": "Tablette",
        "wirkstoffbezeichnung": "Ibuprofen",
        "applikationshinweis": "Nehmen Sie das Arzneimittel mit Flüssigkeit (z.B. 1 Glas Wasser) ein.",
        "name": "Miske",
        "vorname": "Alex",
        "anschrift": "Augustdorf",
        "telefonnummer": 12345678,
        "aufnahmedatum": "2015-12-31T23:00:00.000Z",
        "entlassungsdatum": "2016-01-11T23:00:00.000Z",
        "geburtsdatum": "1989-09-15T22:00:00.000Z",
        "krankenversicherung": "AOK",
        "grund": "Aua",
        "zimmer": 1
    }, {
        "medikament_id": 2,
        "verordnung_id": 2,
        "applikationszeitpunkt": "[{\"tag\":\"Montag\",\"zeiten\": [{\"zeit\":\"08:00\"}, {\"zeit\":\"16:00\"}]},{\"tag\":\"Mittwoch\",\"zeiten\": [{\"zeit\":\"08:00\"}, {\"zeit\":\"16:00\"}]}]",
        "beginn": "2015-12-31T23:00:00.000Z",
        "ende": "2016-01-10T23:00:00.000Z",
        "patient_id": 2,
        "personal_id": 2,
        "station_id": 1,
        "dosierung": 1,
        "selbstverordnung": 1,
        "medikamentname": "IBUFLAM 800mg",
        "darreichungsform": "peroral",
        "wirkstärke": 800,
        "einheit": "Tablette",
        "wirkstoffbezeichnung": "Ibuprofen",
        "applikationshinweis": "Nehmen Sie das Arzneimittel mit Flüssigkeit (z.B. 1 Glas Wasser) ein.",
        "name": "Mustermann",
        "vorname": "Max",
        "anschrift": "Musterhausen",
        "telefonnummer": 12345678,
        "aufnahmedatum": "2016-01-04T23:00:00.000Z",
        "entlassungsdatum": "2016-01-26T23:00:00.000Z",
        "geburtsdatum": "1980-10-10T22:00:00.000Z",
        "krankenversicherung": "AOK",
        "grund": "Auch Aua",
        "zimmer": 2
    }, {
        "medikament_id": 2,
        "verordnung_id": 3,
        "applikationszeitpunkt": "[{\"tag\":\"Montag\",\"zeiten\": [{\"zeit\":\"08:00\"}, {\"zeit\":\"16:00\"}]},{\"tag\":\"Mittwoch\",\"zeiten\": [{\"zeit\":\"08:00\"}, {\"zeit\":\"16:00\"}]}]",
        "beginn": "2015-12-31T23:00:00.000Z",
        "ende": "2016-01-10T23:00:00.000Z",
        "patient_id": 1,
        "personal_id": 2,
        "station_id": 1,
        "dosierung": 1,
        "selbstverordnung": 0,
        "medikamentname": "IBUFLAM 800mg",
        "darreichungsform": "peroral",
        "wirkstärke": 800,
        "einheit": "Tablette",
        "wirkstoffbezeichnung": "Ibuprofen",
        "applikationshinweis": "Nehmen Sie das Arzneimittel mit Flüssigkeit (z.B. 1 Glas Wasser) ein.",
        "name": "Miske",
        "vorname": "Alex",
        "anschrift": "Augustdorf",
        "telefonnummer": 12345678,
        "aufnahmedatum": "2015-12-31T23:00:00.000Z",
        "entlassungsdatum": "2016-01-11T23:00:00.000Z",
        "geburtsdatum": "1989-09-15T22:00:00.000Z",
        "krankenversicherung": "AOK",
        "grund": "Aua",
        "zimmer": 1
    }, {
        "medikament_id": 2,
        "verordnung_id": 3,
        "applikationszeitpunkt": "[{\"tag\":\"Montag\",\"zeiten\": [{\"zeit\":\"08:00\"}, {\"zeit\":\"16:00\"}]},{\"tag\":\"Mittwoch\",\"zeiten\": [{\"zeit\":\"08:00\"}, {\"zeit\":\"16:00\"}]}]",
        "beginn": "2015-12-31T23:00:00.000Z",
        "ende": "2016-01-10T23:00:00.000Z",
        "patient_id": 2,
        "personal_id": 2,
        "station_id": 1,
        "dosierung": 1,
        "selbstverordnung": 0,
        "medikamentname": "IBUFLAM 800mg",
        "darreichungsform": "peroral",
        "wirkstärke": 800,
        "einheit": "Tablette",
        "wirkstoffbezeichnung": "Ibuprofen",
        "applikationshinweis": "Nehmen Sie das Arzneimittel mit Flüssigkeit (z.B. 1 Glas Wasser) ein.",
        "name": "Mustermann",
        "vorname": "Max",
        "anschrift": "Musterhausen",
        "telefonnummer": 12345678,
        "aufnahmedatum": "2016-01-04T23:00:00.000Z",
        "entlassungsdatum": "2016-01-26T23:00:00.000Z",
        "geburtsdatum": "1980-10-10T22:00:00.000Z",
        "krankenversicherung": "AOK",
        "grund": "Auch Aua",
        "zimmer": 2
    }]
